cuebit/__init__.py
cuebit/cli.py
cuebit/dashboard.py
cuebit/registry.py
cuebit/server.py
cuebit-0.2.1.dist-info/licenses/LICENSE
cuebit-0.2.1.dist-info/METADATA
cuebit-0.2.1.dist-info/WHEEL
cuebit-0.2.1.dist-info/entry_points.txt
cuebit-0.2.1.dist-info/top_level.txt
cuebit-0.2.1.dist-info/RECORD
